reproschema/__init__.py
reproschema/_version.py
reproschema/cli.py
reproschema/context_url.py
reproschema/convertutils.py
reproschema/jsonldutils.py
reproschema/loris2reproschema.py
reproschema/migrate.py
reproschema/nbdc2reproschema.py
reproschema/nbdc_mappings.py
reproschema/output2redcap.py
reproschema/redcap2reproschema.py
reproschema/redcap_mappings.py
reproschema/reproschema2fhir.py
reproschema/reproschema2redcap.py
reproschema/utils.py
reproschema/validate.py
reproschema/example/fhir/fhir_output/q_generic_gad7_anxiety/q_generic_gad7_anxiety.json
reproschema/example/fhir/reproschema2fhir_data_example/activities/q_generic_gad7_anxiety/q_generic_gad7_anxiety_schema
reproschema/example/fhir/reproschema2fhir_data_example/activities/q_generic_gad7_anxiety/items/afraid_of_things
reproschema/example/fhir/reproschema2fhir_data_example/activities/q_generic_gad7_anxiety/items/cant_control_worry
reproschema/example/fhir/reproschema2fhir_data_example/activities/q_generic_gad7_anxiety/items/easily_agitated
reproschema/example/fhir/reproschema2fhir_data_example/activities/q_generic_gad7_anxiety/items/gad_7_completed_at
reproschema/example/fhir/reproschema2fhir_data_example/activities/q_generic_gad7_anxiety/items/gad_7_duration
reproschema/example/fhir/reproschema2fhir_data_example/activities/q_generic_gad7_anxiety/items/gad_7_session_id
reproschema/example/fhir/reproschema2fhir_data_example/activities/q_generic_gad7_anxiety/items/gad_7_started_at
reproschema/example/fhir/reproschema2fhir_data_example/activities/q_generic_gad7_anxiety/items/hard_to_sit_still
reproschema/example/fhir/reproschema2fhir_data_example/activities/q_generic_gad7_anxiety/items/nervous_anxious
reproschema/example/fhir/reproschema2fhir_data_example/activities/q_generic_gad7_anxiety/items/tough_to_work
reproschema/example/fhir/reproschema2fhir_data_example/activities/q_generic_gad7_anxiety/items/trouble_relaxing
reproschema-1.1.0.dist-info/METADATA
reproschema-1.1.0.dist-info/WHEEL
reproschema-1.1.0.dist-info/entry_points.txt
reproschema-1.1.0.dist-info/licenses/LICENSE
reproschema-1.1.0.dist-info/RECORD
